NanoPcap/Format.py
NanoPcap/Listener.py
NanoPcap/Parser.py
NanoPcap/__init__.py
NanoPcap/Protocols/Ethernet.py
NanoPcap/Protocols/IPv4.py
NanoPcap/Protocols/__init__.py
NanoPcap/Tools/Dump.py
NanoPcap/Tools/Filter.py
NanoPcap/Tools/Merge.py
NanoPcap/Tools/Split.py
NanoPcap/Tools/SplitFlows.py
NanoPcap/Tools/Summary.py
NanoPcap/Tools/__init__.py
NanoPcap/Utility/Data.py
NanoPcap/Utility/Statistics.py
NanoPcap/Utility/Units.py
NanoPcap/Utility/__init__.py
NanoPcap-1.0.4.dist-info/LICENSE
NanoPcap-1.0.4.dist-info/METADATA
NanoPcap-1.0.4.dist-info/WHEEL
NanoPcap-1.0.4.dist-info/top_level.txt
NanoPcap-1.0.4.dist-info/RECORD
