Metadata-Version: 2.1
Name: NanoPcap
Version: 1.0.4
Summary: PCAP tools and parsing library with nanosecond support and without dependencies
Home-page: https://github.com/AgalmicVentures/NanoPcap
Author: Ian Hutchinson
Author-email: ihutchinson@agalmicventures.com
License: MIT
Classifier: License :: OSI Approved :: MIT License
Classifier: Operating System :: OS Independent
Classifier: Programming Language :: Python :: 3
Classifier: Topic :: Internet :: Log Analysis
Classifier: Topic :: System :: Networking
Classifier: Topic :: Utilities
License-File: LICENSE
